pyfletchgen-0.0.20.dist-info/entry_points.txt
pyfletchgen-0.0.20.dist-info/WHEEL
pyfletchgen-0.0.20.dist-info/top_level.txt
pyfletchgen-0.0.20.dist-info/RECORD
pyfletchgen-0.0.20.dist-info/METADATA
pyfletchgen/lib.cpython-39-x86_64-linux-gnu.so
pyfletchgen/__init__.py
pyfletchgen.libs/libfletchgen_lib-47fc9b27.so
pyfletchgen.libs/libarrow-777f8346.so.500
pyfletchgen.libs/libarrow_python-5465ffd7.so.500
