Metadata-Version: 2.1
Name: pyfletchgen
Version: 0.0.20
Summary: UNKNOWN
Home-page: https://github.com/abs-tudelft/fletcher
Author: Accelerated Big Data Systems, Delft University of Technology
License: Apache License, Version 2.0
Project-URL: Bug Tracker, https://github.com/abs-tudelft/fletcher/issues
Project-URL: Documentation, https://abs-tudelft.github.io/fletcher/
Project-URL: Source Code, https://github.com/abs-tudelft/fletcher/
Platform: UNKNOWN
Classifier: Programming Language :: Python :: 3
Classifier: Programming Language :: Cython
Classifier: Intended Audience :: Developers
Classifier: License :: OSI Approved :: Apache Software License
Classifier: Operating System :: POSIX :: Linux
Requires-Dist: numpy (>=1.14)
Requires-Dist: pandas
Requires-Dist: pyarrow (==5.0.0)
